mmguero/__init__.py
mmguero/caselessdictionary.py
mmguero/mmguero.py
mmguero-2.0.4.dist-info/METADATA
mmguero-2.0.4.dist-info/WHEEL
mmguero-2.0.4.dist-info/entry_points.txt
mmguero-2.0.4.dist-info/licenses/LICENSE
mmguero-2.0.4.dist-info/RECORD
