Metadata-Version: 2.4
Name: mmguero
Version: 2.0.4
Summary: Seth Grover's useful Python helpers
Project-URL: Homepage, https://github.com/mmguero/python-mmguero
Project-URL: Issues, https://github.com/mmguero/python-mmguero/issues
Project-URL: Repository, https://github.com/mmguero/python-mmguero.git
Author-email: Seth Grover <mero.mero.guero@gmail.com>
License-File: LICENSE
Classifier: License :: OSI Approved :: MIT License
Classifier: Operating System :: OS Independent
Classifier: Programming Language :: Python :: 3
Classifier: Topic :: Utilities
Requires-Python: >=3.9
